photo_layout/__init__.py
photo_layout/image.py
photo_layout/layout.py
photo_layout/version.py
photo_layout-1.0.5.dist-info/LICENSE
photo_layout-1.0.5.dist-info/METADATA
photo_layout-1.0.5.dist-info/WHEEL
photo_layout-1.0.5.dist-info/top_level.txt
photo_layout-1.0.5.dist-info/RECORD
