Metadata-Version: 2.1
Name: photo-layout
Version: 1.0.5
Summary: Photo Layout
Home-page: https://github.com/zhenzi0322/photo-layout
Author: 玉振
Author-email: 82131529@qq.com
License: MIT License
Keywords: photo-layout
Classifier: Development Status :: 4 - Beta
Classifier: Intended Audience :: Developers
Classifier: License :: OSI Approved :: MIT License
Classifier: Programming Language :: Python
Classifier: Programming Language :: Python :: 3
Classifier: Programming Language :: Python :: 3.7
Classifier: Programming Language :: Python :: 3.8
Classifier: Programming Language :: Python :: 3.9
Classifier: Programming Language :: Python :: 3.10
Classifier: Topic :: Multimedia :: Graphics
Classifier: Topic :: Multimedia :: Graphics :: Viewers
Classifier: Topic :: Multimedia :: Graphics :: Graphics Conversion
Requires-Python: >=3
License-File: LICENSE
Requires-Dist: pillow (>=8.4.0)
Requires-Dist: pydantic (>=1.9.0)
